skill_demo/LICENSE.md
skill_demo/README.md
skill_demo/__init__.py
skill_demo/skill.json
skill_demo/version.py
skill_demo/locale/en-us/ask_demo.dialog
skill_demo/locale/en-us/ask_demo_next_time.dialog
skill_demo/locale/en-us/confirm_demo_disabled.dialog
skill_demo/locale/en-us/confirm_demo_enabled.dialog
skill_demo/locale/en-us/demo.txt
skill_demo/locale/en-us/finished_demo.dialog
skill_demo/locale/en-us/mall_demo.txt
skill_demo/locale/en-us/show_demo.intent
skill_demo/locale/en-us/starting_demo.dialog
skill_demo/locale/uk-ua/ask_demo.dialog
skill_demo/locale/uk-ua/ask_demo_next_time.dialog
skill_demo/locale/uk-ua/confirm_demo_disabled.dialog
skill_demo/locale/uk-ua/confirm_demo_enabled.dialog
skill_demo/locale/uk-ua/demo.txt
skill_demo/locale/uk-ua/finished_demo.dialog
skill_demo/locale/uk-ua/show_demo.intent
skill_demo/locale/uk-ua/starting_demo.dialog
skill_demo/neon_skill_demo.egg-info/PKG-INFO
skill_demo/neon_skill_demo.egg-info/SOURCES.txt
skill_demo/neon_skill_demo.egg-info/dependency_links.txt
skill_demo/neon_skill_demo.egg-info/entry_points.txt
skill_demo/neon_skill_demo.egg-info/requires.txt
skill_demo/neon_skill_demo.egg-info/top_level.txt
skill_demo/test/test_skill.py
neon_skill_demo-1.0.4.dist-info/LICENSE.md
neon_skill_demo-1.0.4.dist-info/METADATA
neon_skill_demo-1.0.4.dist-info/WHEEL
neon_skill_demo-1.0.4.dist-info/entry_points.txt
neon_skill_demo-1.0.4.dist-info/top_level.txt
neon_skill_demo-1.0.4.dist-info/RECORD
