Metadata-Version: 2.1
Name: neon-skill-demo
Version: 1.0.4
Home-page: https://github.com/NeonGeckoCom/skill-demo
Author: Neongecko
Author-email: developers@neon.ai
License: BSD-3-Clause
License-File: LICENSE.md
Requires-Dist: neon-utils~=1.8
Requires-Dist: neon-tts-plugin-audiofiles~=0.0.3
Requires-Dist: ovos-plugin-manager>0.0.21,~=0.0
Requires-Dist: ovos-utils>=0.0.28,~=0.0
Requires-Dist: ovos-bus-client>=0.0.3,~=0.0
Requires-Dist: ovos-workshop~=0.0
Provides-Extra: test
Requires-Dist: neon-minerva[padatious]~=0.3; extra == "test"
